pydantic_ai_visual/__init__.py
pydantic_ai_visual/app.py
pydantic_ai_visual/cli.py
pydantic_ai_visual/log.py
pydantic_ai_visual-0.1.2.dist-info/METADATA
pydantic_ai_visual-0.1.2.dist-info/WHEEL
pydantic_ai_visual-0.1.2.dist-info/entry_points.txt
pydantic_ai_visual-0.1.2.dist-info/licenses/LICENSE
pydantic_ai_visual-0.1.2.dist-info/RECORD
