Metadata-Version: 2.4
Name: pydantic-ai-visual
Version: 0.1.2
Summary: pydantic-ai messages visualization
Project-URL: Homepage, https://wh1isper.github.io/pydantic-ai-visual/
Project-URL: Repository, https://github.com/wh1isper/pydantic-ai-visual
Project-URL: Documentation, https://wh1isper.github.io/pydantic-ai-visual/
Author-email: Wh1isper <jizhongsheng957@gmail.com>
License-File: LICENSE
Keywords: python
Classifier: Intended Audience :: Developers
Classifier: Programming Language :: Python
Classifier: Programming Language :: Python :: 3
Classifier: Programming Language :: Python :: 3.9
Classifier: Programming Language :: Python :: 3.10
Classifier: Programming Language :: Python :: 3.11
Classifier: Programming Language :: Python :: 3.12
Classifier: Programming Language :: Python :: 3.13
Classifier: Topic :: Software Development :: Libraries :: Python Modules
Requires-Python: <4.0,>=3.9
Requires-Dist: click>=8.1.8
Requires-Dist: gradio>=4.44.1
Requires-Dist: httpx>=0.28.1
Requires-Dist: loguru>=0.7.3
Requires-Dist: pydantic-ai-slim>=0.1.3
